plot_wav/__init__.py
plot_wav/core.py
plot_wav-0.1.0.dist-info/METADATA
plot_wav-0.1.0.dist-info/WHEEL
plot_wav-0.1.0.dist-info/entry_points.txt
plot_wav-0.1.0.dist-info/top_level.txt
plot_wav-0.1.0.dist-info/RECORD
