Metadata-Version: 2.1
Name: plot-wav
Version: 0.1.0
Summary: UNKNOWN
Home-page: https://github.com/averak/plot-wav
Author: Tatsuya Abe
Author-email: abe12@mccc.jp
License: MIT
Keywords: wave spectrogram MFCC audio
Platform: UNKNOWN
Classifier: License :: OSI Approved :: MIT License
Classifier: Programming Language :: Python :: 3.8
Requires-Dist: argparse
Requires-Dist: numpy
Requires-Dist: matplotlib
Requires-Dist: librosa
Requires-Dist: scipy
Requires-Dist: wave
